[
	{
		"name": "Design",
		"Essentiel": "Sobre",
		"Premium": "Travaillé"
	},
	{
		"name": "Direction artistique",
		"Essentiel": "Polices et couleurs",
		"Premium": "Pour tout le site"
	},
	{
		"name": "Animations",
		"Essentiel": "Simples",
		"Premium": "Poussées"
	},
	{
		"name": "Nombre de pages incluses",
		"Essentiel": "3",
		"Premium": "5"
	},
	{
		"name": "Contenu administrable",
		"Essentiel": "❌",
		"Premium": "✔️"
	},
	{
		"name": "Demandes de changements en cours de développement",
		"Essentiel": "Jusqu'à 2",
		"Premium": "Jusqu'à 5"
	},
	{
		"name": "Intégration du design",
		"Essentiel": "✔️",
		"Premium": "✔️"
	},
	{
		"name": "Référencement local de l'entreprise",
		"Essentiel": "✔️",
		"Premium": "✔️"
	},
	{
		"name": "Référencement par mots clés",
		"Essentiel": "✔️",
		"Premium": "✔️"
	},
	{
		"name": "Liens vers vos médias sociaux",
		"Essentiel": "✔️",
		"Premium": "✔️"
	},
	{
		"name": "Audit",
		"Essentiel": "✔️",
		"Premium": "✔️"
	},
	{
		"name": "Optimisation des performances",
		"Essentiel": "✔️",
		"Premium": "✔️"
	}
]
